nipyapi/__init__.py
nipyapi/_version.py
nipyapi/bulletins.py
nipyapi/canvas.py
nipyapi/cli.py
nipyapi/config.py
nipyapi/extensions.py
nipyapi/layout.py
nipyapi/nifi_registry.py
nipyapi/nipyapi.code-workspace
nipyapi/parameters.py
nipyapi/profiles.py
nipyapi/security.py
nipyapi/system.py
nipyapi/utils.py
nipyapi/versioning.py
nipyapi/ci/__init__.py
nipyapi/ci/change_flow_version.py
nipyapi/ci/cleanup.py
nipyapi/ci/commit_flow.py
nipyapi/ci/configure_inherited_params.py
nipyapi/ci/configure_params.py
nipyapi/ci/delete_nar.py
nipyapi/ci/deploy_flow.py
nipyapi/ci/detach_flow.py
nipyapi/ci/ensure_registry.py
nipyapi/ci/export_flow_definition.py
nipyapi/ci/export_parameters.py
nipyapi/ci/get_flow_diff.py
nipyapi/ci/get_flow_versions.py
nipyapi/ci/get_status.py
nipyapi/ci/import_flow_definition.py
nipyapi/ci/list_flows.py
nipyapi/ci/list_nars.py
nipyapi/ci/list_registry_flows.py
nipyapi/ci/purge_flowfiles.py
nipyapi/ci/resolve_git_ref.py
nipyapi/ci/revert_flow.py
nipyapi/ci/start_flow.py
nipyapi/ci/stop_flow.py
nipyapi/ci/upload_asset.py
nipyapi/ci/upload_nar.py
nipyapi/ci/verify_config.py
nipyapi/nifi/__init__.py
nipyapi/nifi/api_client.py
nipyapi/nifi/configuration.py
nipyapi/nifi/rest.py
nipyapi/nifi/apis/__init__.py
nipyapi/nifi/apis/access_api.py
nipyapi/nifi/apis/authentication_api.py
nipyapi/nifi/apis/connections_api.py
nipyapi/nifi/apis/controller_api.py
nipyapi/nifi/apis/controller_services_api.py
nipyapi/nifi/apis/counters_api.py
nipyapi/nifi/apis/data_transfer_api.py
nipyapi/nifi/apis/flow_api.py
nipyapi/nifi/apis/flow_file_queues_api.py
nipyapi/nifi/apis/funnels_api.py
nipyapi/nifi/apis/input_ports_api.py
nipyapi/nifi/apis/labels_api.py
nipyapi/nifi/apis/output_ports_api.py
nipyapi/nifi/apis/parameter_contexts_api.py
nipyapi/nifi/apis/parameter_providers_api.py
nipyapi/nifi/apis/policies_api.py
nipyapi/nifi/apis/process_groups_api.py
nipyapi/nifi/apis/processors_api.py
nipyapi/nifi/apis/provenance_api.py
nipyapi/nifi/apis/provenance_events_api.py
nipyapi-1.5.0.dist-info/licenses/LICENSE
nipyapi-1.5.0.dist-info/licenses/NOTICE
nipyapi-1.5.0.dist-info/METADATA
nipyapi-1.5.0.dist-info/WHEEL
nipyapi-1.5.0.dist-info/entry_points.txt
nipyapi-1.5.0.dist-info/top_level.txt
nipyapi-1.5.0.dist-info/RECORD
