Metadata-Version: 2.4
Name: nipyapi
Version: 1.5.0
Summary: A rich Apache NiFi Python Client SDK
Author-email: NiPyAPI maintainers <chaffelson@gmail.com>
License-Expression: Apache-2.0
Project-URL: Homepage, https://github.com/Chaffelson/nipyapi
Project-URL: Repository, https://github.com/Chaffelson/nipyapi.git
Project-URL: Documentation, https://nipyapi.readthedocs.io/en/latest/
Project-URL: Issues, https://github.com/Chaffelson/nipyapi/issues
Keywords: nipyapi,nifi,apache nifi,client,sdk
Classifier: Development Status :: 4 - Beta
Classifier: Intended Audience :: Developers
Classifier: Intended Audience :: System Administrators
Classifier: Natural Language :: English
Classifier: Operating System :: OS Independent
Classifier: Programming Language :: Python :: 3
Classifier: Programming Language :: Python :: 3.9
Classifier: Programming Language :: Python :: 3.10
Classifier: Programming Language :: Python :: 3.11
Classifier: Programming Language :: Python :: 3.12
Classifier: Topic :: Software Development :: Libraries
Requires-Python: >=3.9
License-File: LICENSE
License-File: NOTICE
Requires-Dist: setuptools>=38.5
Requires-Dist: packaging>=17.1
Requires-Dist: urllib3<3,>=1.26
Requires-Dist: certifi>=2023.7.22
Requires-Dist: requests>=2.18
Requires-Dist: pysocks>=1.7.1
Requires-Dist: PyYAML>=6.0
Provides-Extra: cli
Requires-Dist: fire>=0.5.0; extra == "cli"
Provides-Extra: dev
Requires-Dist: build>=1.0.0; extra == "dev"
Requires-Dist: setuptools-scm[toml]>=8; extra == "dev"
Requires-Dist: flake8>=3.6.0; extra == "dev"
Requires-Dist: pylint>=3.3.0; extra == "dev"
Requires-Dist: black>=24.8.0; extra == "dev"
Requires-Dist: isort>=5.13.2; extra == "dev"
Requires-Dist: coverage>=7.0; extra == "dev"
Requires-Dist: pytest>=8.4; extra == "dev"
Requires-Dist: pytest-cov>=5.0.0; extra == "dev"
Requires-Dist: codecov>=2.1.13; extra == "dev"
Requires-Dist: deepdiff>=3.3.0; extra == "dev"
Requires-Dist: twine>=6.0.0; extra == "dev"
Requires-Dist: pre-commit>=3.0.0; extra == "dev"
Requires-Dist: fire>=0.5.0; extra == "dev"
Provides-Extra: docs
Requires-Dist: Sphinx>=7.4.0; extra == "docs"
Requires-Dist: sphinx_rtd_theme>=3.0.0; extra == "docs"
Requires-Dist: sphinxcontrib-jquery>=4.1; extra == "docs"
Dynamic: license-file
